pydantic2django/__init__.py
pydantic2django/entrypoint.py
pydantic2django/core/__init__.py
pydantic2django/core/base_generator.py
pydantic2django/core/bidirectional_mapper.py
pydantic2django/core/context.py
pydantic2django/core/defs.py
pydantic2django/core/discovery.py
pydantic2django/core/factories.py
pydantic2django/core/filter_helpers.py
pydantic2django/core/imports.py
pydantic2django/core/mapping_units.py
pydantic2django/core/relationships.py
pydantic2django/core/serialization.py
pydantic2django/core/typing.py
pydantic2django/core/utils/__init__.py
pydantic2django/core/utils/naming.py
pydantic2django/core/utils/relationships.py
pydantic2django/core/utils/strings.py
pydantic2django/core/utils/timescale.py
pydantic2django/dataclass/__init__.py
pydantic2django/dataclass/discovery.py
pydantic2django/dataclass/factory.py
pydantic2django/dataclass/generator.py
pydantic2django/django/README_static_models.md
pydantic2django/django/__init__.py
pydantic2django/django/admin.py
pydantic2django/django/conversion.py
pydantic2django/django/models.py
pydantic2django/django/typing.py
pydantic2django/django/templates/context_class.py.j2
pydantic2django/django/templates/imports_block.py.j2
pydantic2django/django/templates/model_definition.py.j2
pydantic2django/django/templates/models_file.py.j2
pydantic2django/django/timescale/__init__.py
pydantic2django/django/timescale/bases.py
pydantic2django/django/timescale/heuristics.py
pydantic2django/django/utils/__init__.py
pydantic2django/django/utils/naming.py
pydantic2django/django/utils/serialization.py
pydantic2django/pydantic/__init__.py
pydantic2django/pydantic/discovery.py
pydantic2django/pydantic/factory.py
pydantic2django/pydantic/generator.py
pydantic2django/pydantic/utils/__init__.py
pydantic2django/pydantic/utils/introspection.py
pydantic2django/typedclass/README.md
pydantic2django/typedclass/__init__.py
pydantic2django/typedclass/discovery.py
pydantic2django/typedclass/factory.py
pydantic2django/typedclass/generator.py
django_typed2django-1.0.20.dist-info/METADATA
django_typed2django-1.0.20.dist-info/WHEEL
django_typed2django-1.0.20.dist-info/RECORD
