Metadata-Version: 2.4
Name: django-typed2django
Version: 1.0.20
Summary: Convert Various non-Django models to Django models dynamically
Author-email: Lucas Whipple <lucas@lodbrok.app>
License: MIT
Classifier: Development Status :: 3 - Alpha
Classifier: Framework :: Django
Classifier: Intended Audience :: Developers
Classifier: Topic :: Software Development :: Libraries :: Python Modules
Requires-Python: >=3.11
Requires-Dist: django-timescaledb>=0.2.13
Requires-Dist: django>=4.0
Requires-Dist: email-validator>=2.1.0
Requires-Dist: lxml>=6.0.1
Requires-Dist: mkdocs-autolinks-plugin>=0.7.1
Requires-Dist: pre-commit>=4.1.0
Requires-Dist: pydantic>=2.0
